mdio/__init__.py
mdio/__main__.py
mdio/api/__init__.py
mdio/api/io.py
mdio/builder/__init__.py
mdio/builder/dataset_builder.py
mdio/builder/formatting_html.py
mdio/builder/schemas/__init__.py
mdio/builder/schemas/base.py
mdio/builder/schemas/chunk_grid.py
mdio/builder/schemas/compressors.py
mdio/builder/schemas/core.py
mdio/builder/schemas/dimension.py
mdio/builder/schemas/dtype.py
mdio/builder/schemas/units.py
mdio/builder/schemas/v1/__init__.py
mdio/builder/schemas/v1/dataset.py
mdio/builder/schemas/v1/stats.py
mdio/builder/schemas/v1/units.py
mdio/builder/schemas/v1/variable.py
mdio/builder/template_registry.py
mdio/builder/templates/__init__.py
mdio/builder/templates/base.py
mdio/builder/templates/seismic_2d_cdp.py
mdio/builder/templates/seismic_2d_poststack.py
mdio/builder/templates/seismic_2d_streamer_shot.py
mdio/builder/templates/seismic_3d_cdp.py
mdio/builder/templates/seismic_3d_coca.py
mdio/builder/templates/seismic_3d_poststack.py
mdio/builder/templates/seismic_3d_streamer_field.py
mdio/builder/templates/seismic_3d_streamer_shot.py
mdio/builder/templates/types.py
mdio/builder/xarray_builder.py
mdio/commands/__init__.py
mdio/commands/copy.py
mdio/commands/info.py
mdio/commands/segy.py
mdio/constants.py
mdio/converters/__init__.py
mdio/converters/exceptions.py
mdio/converters/mdio.py
mdio/converters/segy.py
mdio/converters/type_converter.py
mdio/core/__init__.py
mdio/core/config.py
mdio/core/dimension.py
mdio/core/grid.py
mdio/core/indexing.py
mdio/core/utils_write.py
mdio/core/zarr_io.py
mdio/exceptions.py
mdio/optimize/__init__.py
mdio/optimize/access_pattern.py
mdio/optimize/common.py
mdio/optimize/patch.py
mdio/py.typed
mdio/segy/__init__.py
mdio/segy/_raw_trace_wrapper.py
mdio/segy/_workers.py
mdio/segy/blocked_io.py
mdio/segy/compat.py
mdio/segy/creation.py
mdio/segy/exceptions.py
mdio/segy/file.py
mdio/segy/geometry.py
mdio/segy/helpers_segy.py
mdio/segy/parsers.py
mdio/segy/scalar.py
mdio/segy/utilities.py
multidimio-1.1.2.dist-info/licenses/LICENSE
multidimio-1.1.2.dist-info/WHEEL
multidimio-1.1.2.dist-info/entry_points.txt
multidimio-1.1.2.dist-info/METADATA
multidimio-1.1.2.dist-info/RECORD
