Metadata-Version: 2.4
Name: multidimio
Version: 1.1.2
Summary: Cloud-native, scalable, and user-friendly multi dimensional energy data!
Keywords: mdio,multidimio,seismic,wind,data
Author: Altay Sansal
Author-email: Altay Sansal <altay.sansal@tgs.com>
License-Expression: Apache-2.0
License-File: LICENSE
Classifier: Programming Language :: Python :: 3
Classifier: Programming Language :: Python :: 3.11
Classifier: Programming Language :: Python :: 3.12
Classifier: Programming Language :: Python :: 3.13
Classifier: License :: OSI Approved :: Apache Software License
Classifier: Development Status :: 4 - Beta
Requires-Dist: click>=8.3.0
Requires-Dist: click-params>=0.5.0
Requires-Dist: dask>=2025.9.1
Requires-Dist: fsspec>=2025.9.0
Requires-Dist: pint>=0.25.0
Requires-Dist: psutil>=7.1.0
Requires-Dist: pydantic>=2.12.0
Requires-Dist: pydantic-settings>=2.6.1
Requires-Dist: rich>=14.1.0
Requires-Dist: segy>=0.5.3
Requires-Dist: tqdm>=4.67.1
Requires-Dist: universal-pathlib>=0.3.3
Requires-Dist: xarray>=2025.10.1
Requires-Dist: zarr>=3.1.3
Requires-Dist: s3fs>=2025.9.0 ; extra == 'cloud'
Requires-Dist: gcsfs>=2025.9.0 ; extra == 'cloud'
Requires-Dist: adlfs>=2025.8.0 ; extra == 'cloud'
Requires-Dist: distributed>=2025.9.1 ; extra == 'distributed'
Requires-Dist: bokeh>=3.8.0 ; extra == 'distributed'
Requires-Dist: zfpy>=1.0.1 ; extra == 'lossy'
Requires-Python: >=3.11, <3.14
Project-URL: documentation, https://mdio-python.readthedocs.io
Project-URL: homepage, https://mdio.dev/
Project-URL: repository, https://github.com/TGSAI/mdio-python
Provides-Extra: cloud
Provides-Extra: distributed
Provides-Extra: lossy
